{"cameraMode":{"drawMode":0,"name":"Shaded","section":"Shading Mode"},"sceneLighting":false,"audioPlay":false,"sceneViewState":{"m_AlwaysRefresh":false,"showFog":true,"showSkybox":false,"showFlares":true,"showImageEffects":true,"showParticleSystems":true,"showVisualEffectGraphs":true,"m_FxEnabled":true},"in2DMode":false,"pivot":{"x":-2.8686859607696535,"y":-9.492634773254395,"z":19.60426139831543},"rotation":{"x":-0.4354028105735779,"y":0.5054652094841003,"z":-0.32938966155052187,"w":-0.6682157516479492},"size":18.557682037353517,"orthographic":false}